polygon_pascalvoc_writer/__init__.py
polygon_pascalvoc_writer/voc_writer.py
polygon_pascalvoc_writer/templates/annotation.xml
polygon_pascalvoc_writer-1.0.5.dist-info/LICENSE
polygon_pascalvoc_writer-1.0.5.dist-info/METADATA
polygon_pascalvoc_writer-1.0.5.dist-info/WHEEL
polygon_pascalvoc_writer-1.0.5.dist-info/top_level.txt
polygon_pascalvoc_writer-1.0.5.dist-info/RECORD
