Metadata-Version: 2.1
Name: polygon-pascalvoc-writer
Version: 1.0.5
Summary: For generating Pascal VOC XML image annotation files
Home-page: https://github.com/EvitanRelta/polygon-pascalvoc-writer
Author: EvitanRelta
Author-email: shauntanzongzhi@gmail.com
License: MIT
Keywords: polygon pascal voc pascalvoc annotation writer xml python
Platform: UNKNOWN
License-File: LICENSE
Requires-Dist: jinja2
